chaw/__init__.py
chaw/chaw.py
chaw-0.0.3.dist-info/METADATA
chaw-0.0.3.dist-info/WHEEL
chaw-0.0.3.dist-info/top_level.txt
chaw-0.0.3.dist-info/RECORD
