Metadata-Version: 2.1
Name: chaw
Version: 0.0.3
Summary: Wrapper for the Companies House API
Author: Morgan Thomas
Author-email: morgan@morganthomas.uk
Keywords: python,companies house,uk,government,businesses
Requires-Dist: requests (>=2.31.0)
